odoo/addons/datamodel/README.rst
odoo/addons/datamodel/__init__.py
odoo/addons/datamodel/__manifest__.py
odoo/addons/datamodel/builder.py
odoo/addons/datamodel/core.py
odoo/addons/datamodel/fields.py
odoo/addons/datamodel/datamodels/__init__.py
odoo/addons/datamodel/datamodels/base.py
odoo/addons/datamodel/i18n/datamodel.pot
odoo/addons/datamodel/i18n/es.po
odoo/addons/datamodel/readme/CONTRIBUTORS.rst
odoo/addons/datamodel/readme/DESCRIPTION.rst
odoo/addons/datamodel/readme/ROADMAP.rst
odoo/addons/datamodel/readme/USAGE.rst
odoo/addons/datamodel/static/description/icon.png
odoo/addons/datamodel/static/description/index.html
odoo/addons/datamodel/tests/__init__.py
odoo/addons/datamodel/tests/common.py
odoo/addons/datamodel/tests/test_build_datamodel.py
odoo13_addon_datamodel-13.0.3.0.4.dist-info/METADATA
odoo13_addon_datamodel-13.0.3.0.4.dist-info/WHEEL
odoo13_addon_datamodel-13.0.3.0.4.dist-info/top_level.txt
odoo13_addon_datamodel-13.0.3.0.4.dist-info/RECORD
