Metadata-Version: 2.1
Name: odoo13-addon-datamodel
Version: 13.0.3.0.4
Summary: This addon allows you to define simple data models supporting serialization/deserialization
Home-page: https://github.com/OCA/rest-framework
Author: ACSONE SA/NV, Odoo Community Association (OCA)
Author-email: support@odoo-community.org
License: AGPL-3
Platform: UNKNOWN
Classifier: Programming Language :: Python
Classifier: Framework :: Odoo
Classifier: Framework :: Odoo :: 13.0
Classifier: License :: OSI Approved :: GNU Affero General Public License v3
Classifier: Development Status :: 4 - Beta
Requires-Python: >=3.5
Requires-Dist: marshmallow
Requires-Dist: marshmallow-objects (>=2.0.0)
Requires-Dist: odoo (<13.1dev,>=13.0a)
